tinykernel/__init__.py
tinykernel/_nbdev.py
tinykernel/compilerop.py
tinykernel-0.0.2.dist-info/LICENSE
tinykernel-0.0.2.dist-info/METADATA
tinykernel-0.0.2.dist-info/WHEEL
tinykernel-0.0.2.dist-info/entry_points.txt
tinykernel-0.0.2.dist-info/top_level.txt
tinykernel-0.0.2.dist-info/RECORD
