Metadata-Version: 2.1
Name: tinykernel
Version: 0.0.2
Summary: A minimal Python kernel so you can run Python in your Python
Home-page: https://github.com/fastai/tinykernel/tree/master/
Author: Jeremy Howard
Author-email: j@fast.ai
License: Apache Software License 2.0
Keywords: embedded python fastai nbdev nbprocess ipython kernel
Platform: UNKNOWN
Classifier: Development Status :: 4 - Beta
Classifier: Intended Audience :: Developers
Classifier: Natural Language :: English
Classifier: Programming Language :: Python :: 3.6
Classifier: Programming Language :: Python :: 3.7
Classifier: Programming Language :: Python :: 3.8
Classifier: License :: OSI Approved :: Apache Software License
Requires-Python: >=3.6
